adapters/__init__.py
adapters/composition.py
adapters/context.py
adapters/head_utils.py
adapters/hub_mixin.py
adapters/interface.py
adapters/loading.py
adapters/model_mixin.py
adapters/trainer.py
adapters/training.py
adapters/utils.py
adapters/configuration/__init__.py
adapters/configuration/adapter_config.py
adapters/configuration/adapter_fusion_config.py
adapters/configuration/model_adapters_config.py
adapters/heads/__init__.py
adapters/heads/base.py
adapters/heads/dependency_parsing.py
adapters/heads/language_modeling.py
adapters/heads/model_mixin.py
adapters/methods/__init__.py
adapters/methods/adapter_layer_base.py
adapters/methods/bottleneck.py
adapters/methods/invertible.py
adapters/methods/lora.py
adapters/methods/modeling.py
adapters/methods/prefix_tuning.py
adapters/methods/prompt_tuning.py
adapters/methods/reft.py
adapters/methods/utils.py
adapters/models/__init__.py
adapters/models/albert/__init__.py
adapters/models/albert/adapter_model.py
adapters/models/albert/mixin_albert.py
adapters/models/albert/modeling_albert.py
adapters/models/auto/__init__.py
adapters/models/auto/adapter_model.py
adapters/models/auto/auto_factory.py
adapters/models/bart/__init__.py
adapters/models/bart/adapter_model.py
adapters/models/bart/mixin_bart.py
adapters/models/bart/modeling_bart.py
adapters/models/beit/__init__.py
adapters/models/beit/adapter_model.py
adapters/models/beit/mixin_beit.py
adapters/models/beit/modeling_beit.py
adapters/models/bert/__init__.py
adapters/models/bert/adapter_model.py
adapters/models/bert/mixin_bert.py
adapters/models/bert/modeling_bert.py
adapters/models/bert_generation/__init__.py
adapters/models/bert_generation/adapter_model.py
adapters/models/bert_generation/modeling_bert_generation.py
adapters/models/clip/__init__.py
adapters/models/clip/adapter_model.py
adapters/models/clip/mixin_clip.py
adapters/models/clip/modeling_clip.py
adapters/models/deberta/__init__.py
adapters/models/deberta/adapter_model.py
adapters-1.2.0.dist-info/LICENSE
adapters-1.2.0.dist-info/METADATA
adapters-1.2.0.dist-info/WHEEL
adapters-1.2.0.dist-info/top_level.txt
adapters-1.2.0.dist-info/RECORD
