Metadata-Version: 2.1
Name: adapters
Version: 1.2.0
Summary: A Unified Library for Parameter-Efficient and Modular Transfer Learning
Home-page: https://github.com/adapter-hub/adapters
Author: The AdapterHub team and community contributors
Author-email: calpt@mail.de
License: Apache
Keywords: NLP deep learning transformer pytorch BERT adapters PEFT LoRA
Classifier: Development Status :: 5 - Production/Stable
Classifier: Intended Audience :: Developers
Classifier: Intended Audience :: Education
Classifier: Intended Audience :: Science/Research
Classifier: License :: OSI Approved :: Apache Software License
Classifier: Operating System :: OS Independent
Classifier: Programming Language :: Python :: 3
Classifier: Programming Language :: Python :: 3.9
Classifier: Programming Language :: Python :: 3.10
Classifier: Programming Language :: Python :: 3.11
Classifier: Programming Language :: Python :: 3.12
Classifier: Topic :: Scientific/Engineering :: Artificial Intelligence
Requires-Python: >=3.9.0
License-File: LICENSE
Requires-Dist: transformers~=4.51.3
Requires-Dist: packaging
Provides-Extra: sklearn
Requires-Dist: scikit-learn; extra == "sklearn"
Provides-Extra: torch
Requires-Dist: torch; extra == "torch"
Requires-Dist: accelerate>=0.26.0; extra == "torch"
Provides-Extra: sentencepiece
Requires-Dist: sentencepiece!=0.1.92,>=0.1.91; extra == "sentencepiece"
Requires-Dist: protobuf; extra == "sentencepiece"
Provides-Extra: torchvision
Requires-Dist: torchvision; extra == "torchvision"
Provides-Extra: testing
Requires-Dist: pytest<8.0.0,>=7.2.0; extra == "testing"
Requires-Dist: pytest-rich; extra == "testing"
Requires-Dist: pytest-xdist; extra == "testing"
Requires-Dist: timeout-decorator; extra == "testing"
Requires-Dist: parameterized; extra == "testing"
Requires-Dist: psutil; extra == "testing"
Requires-Dist: datasets!=2.5.0; extra == "testing"
Requires-Dist: dill<0.3.5; extra == "testing"
Requires-Dist: evaluate>=0.2.0; extra == "testing"
Requires-Dist: pytest-timeout; extra == "testing"
Requires-Dist: black~=24.4.0; extra == "testing"
Requires-Dist: sacrebleu<2.0.0,>=1.4.12; extra == "testing"
Requires-Dist: rouge-score!=0.0.7,!=0.0.8,!=0.1,!=0.1.1; extra == "testing"
Requires-Dist: nltk; extra == "testing"
Requires-Dist: GitPython<3.1.19; extra == "testing"
Requires-Dist: sacremoses; extra == "testing"
Requires-Dist: rjieba; extra == "testing"
Requires-Dist: beautifulsoup4; extra == "testing"
Requires-Dist: pillow; extra == "testing"
Requires-Dist: accelerate>=0.26.0; extra == "testing"
Requires-Dist: torchvision; extra == "testing"
Provides-Extra: quality
Requires-Dist: black~=24.4.0; extra == "quality"
Requires-Dist: datasets!=2.5.0; extra == "quality"
Requires-Dist: isort>=5.5.4; extra == "quality"
Requires-Dist: flake8>=3.8.3; extra == "quality"
Requires-Dist: GitPython<3.1.19; extra == "quality"
Provides-Extra: docs
Requires-Dist: docutils==0.16.0; extra == "docs"
Requires-Dist: Jinja2>=3.1.0; extra == "docs"
Requires-Dist: markupsafe==2.0.1; extra == "docs"
Requires-Dist: myst-parser; extra == "docs"
Requires-Dist: sphinx==5.0.2; extra == "docs"
Requires-Dist: sphinx-markdown-tables==0.0.17; extra == "docs"
Requires-Dist: sphinx-rtd-theme==2.0.0; extra == "docs"
Requires-Dist: sphinx-copybutton==0.5.2; extra == "docs"
Requires-Dist: sphinxext-opengraph==0.4.1; extra == "docs"
Requires-Dist: sphinx-intl==2.1.0; extra == "docs"
Requires-Dist: sphinx-multiversion==0.2.4; extra == "docs"
Provides-Extra: dev
Requires-Dist: pytest<8.0.0,>=7.2.0; extra == "dev"
Requires-Dist: pytest-rich; extra == "dev"
Requires-Dist: pytest-xdist; extra == "dev"
Requires-Dist: timeout-decorator; extra == "dev"
Requires-Dist: parameterized; extra == "dev"
Requires-Dist: psutil; extra == "dev"
Requires-Dist: datasets!=2.5.0; extra == "dev"
Requires-Dist: dill<0.3.5; extra == "dev"
Requires-Dist: evaluate>=0.2.0; extra == "dev"
Requires-Dist: pytest-timeout; extra == "dev"
Requires-Dist: black~=24.4.0; extra == "dev"
Requires-Dist: sacrebleu<2.0.0,>=1.4.12; extra == "dev"
Requires-Dist: rouge-score!=0.0.7,!=0.0.8,!=0.1,!=0.1.1; extra == "dev"
Requires-Dist: nltk; extra == "dev"
Requires-Dist: GitPython<3.1.19; extra == "dev"
Requires-Dist: sacremoses; extra == "dev"
Requires-Dist: rjieba; extra == "dev"
Requires-Dist: beautifulsoup4; extra == "dev"
Requires-Dist: pillow; extra == "dev"
Requires-Dist: accelerate>=0.26.0; extra == "dev"
Requires-Dist: torchvision; extra == "dev"
Requires-Dist: torch; extra == "dev"
Requires-Dist: accelerate>=0.26.0; extra == "dev"
Requires-Dist: sentencepiece!=0.1.92,>=0.1.91; extra == "dev"
Requires-Dist: protobuf; extra == "dev"
Requires-Dist: black~=24.4.0; extra == "dev"
Requires-Dist: datasets!=2.5.0; extra == "dev"
Requires-Dist: isort>=5.5.4; extra == "dev"
Requires-Dist: flake8>=3.8.3; extra == "dev"
Requires-Dist: GitPython<3.1.19; extra == "dev"
Requires-Dist: docutils==0.16.0; extra == "dev"
Requires-Dist: Jinja2>=3.1.0; extra == "dev"
Requires-Dist: markupsafe==2.0.1; extra == "dev"
Requires-Dist: myst-parser; extra == "dev"
Requires-Dist: sphinx==5.0.2; extra == "dev"
Requires-Dist: sphinx-markdown-tables==0.0.17; extra == "dev"
Requires-Dist: sphinx-rtd-theme==2.0.0; extra == "dev"
Requires-Dist: sphinx-copybutton==0.5.2; extra == "dev"
Requires-Dist: sphinxext-opengraph==0.4.1; extra == "dev"
Requires-Dist: sphinx-intl==2.1.0; extra == "dev"
Requires-Dist: sphinx-multiversion==0.2.4; extra == "dev"
Requires-Dist: scikit-learn; extra == "dev"
